glest/__init__.py
glest/core.py
glest/helpers.py
glest/plot.py
glest-0.0.1a1.dist-info/WHEEL
glest-0.0.1a1.dist-info/METADATA
glest-0.0.1a1.dist-info/RECORD
