Metadata-Version: 2.1
Name: glest
Version: 0.0.1a1
Summary: Estimate the grouping loss of your probabilistic classifiers.
Author-email: Alexandre Perez-Lebel <alexandre.perez@inria.fr>
Requires-Python: >=3.7
Classifier: Programming Language :: Python :: 3
Classifier: License :: OSI Approved :: MIT License
Classifier: Operating System :: OS Independent
Requires-Dist: numpy
Requires-Dist: scikit-learn
Requires-Dist: matplotlib
Requires-Dist: pre-commit ; extra == "dev"
Requires-Dist: nox ; extra == "dev"
Requires-Dist: sphinx ; extra == "doc"
Requires-Dist: pydata-sphinx-theme ; extra == "doc"
Requires-Dist: sphinx-gallery ; extra == "doc"
Requires-Dist: matplotlib ; extra == "doc"
Requires-Dist: pillow ; extra == "doc"
Requires-Dist: numpy==1.22 ; extra == "oldest_deps"
Requires-Dist: scikit-learn==1.1.3 ; extra == "oldest_deps"
Requires-Dist: pandas==1.5.1 ; extra == "oldest_deps"
Requires-Dist: pytest ; extra == "test"
Requires-Dist: pytest-cov ; extra == "test"
Project-URL: Bug Tracker, https://github.com/aperezlebel/glest/issues
Project-URL: Homepage, https://github.com/aperezlebel/glest
Provides-Extra: dev
Provides-Extra: doc
Provides-Extra: oldest_deps
Provides-Extra: test
